util/__init__.py
util/blocked.py
util/full.py
util/subblocked.py
util/timing.py
blocked_matrix_utils-1.0.9.dist-info/LICENSE.txt
blocked_matrix_utils-1.0.9.dist-info/METADATA
blocked_matrix_utils-1.0.9.dist-info/WHEEL
blocked_matrix_utils-1.0.9.dist-info/top_level.txt
blocked_matrix_utils-1.0.9.dist-info/RECORD
