Metadata-Version: 2.1
Name: blocked-matrix-utils
Version: 1.0.9
Summary: NumPy wrappers for blocked matrices
Home-page: https://github.com/vahtras/util
Author: Olav Vahtras
Author-email: olav.vahtras@gmail.com
License: MIT
Platform: UNKNOWN
Classifier: Development Status :: 5 - Production/Stable
Classifier: Intended Audience :: Science/Research
Classifier: License :: OSI Approved :: GNU General Public License v3 (GPLv3)
Classifier: Programming Language :: Python
Classifier: Programming Language :: Python :: 3
Classifier: Programming Language :: Python :: 3.6
Classifier: Programming Language :: Python :: 3.7
Classifier: Programming Language :: Python :: 3.8
Classifier: Programming Language :: Python :: 3.9
Classifier: Topic :: Scientific/Engineering :: Mathematics
Requires-Dist: scipy
